trytond/modules/pim_memos/README.rst
trytond/modules/pim_memos/__init__.py
trytond/modules/pim_memos/category.py
trytond/modules/pim_memos/category.xml
trytond/modules/pim_memos/ir.py
trytond/modules/pim_memos/memo.py
trytond/modules/pim_memos/memo.xml
trytond/modules/pim_memos/menu.xml
trytond/modules/pim_memos/menuicons.xml
trytond/modules/pim_memos/message.xml
trytond/modules/pim_memos/notereport.py
trytond/modules/pim_memos/notereport.xml
trytond/modules/pim_memos/role_edit.xml
trytond/modules/pim_memos/tryton.cfg
trytond/modules/pim_memos/versiondep.txt
trytond/modules/pim_memos/icon/memo-red-pin.svg
trytond/modules/pim_memos/locale/de.po
trytond/modules/pim_memos/locale/en.po
trytond/modules/pim_memos/report/note.fodt
trytond/modules/pim_memos/report/note.html
trytond/modules/pim_memos/tests/__init__.py
trytond/modules/pim_memos/tests/test_memos.py
trytond/modules/pim_memos/view/category_form.xml
trytond/modules/pim_memos/view/category_list.xml
trytond/modules/pim_memos/view/category_tree.xml
trytond/modules/pim_memos/view/memos_form.xml
trytond/modules/pim_memos/view/memos_list.xml
trytond/modules/pim_memos/view/memos_tree2.xml
mds_pim_memos-7.0.12.dist-info/LICENSE
mds_pim_memos-7.0.12.dist-info/METADATA
mds_pim_memos-7.0.12.dist-info/WHEEL
mds_pim_memos-7.0.12.dist-info/entry_points.txt
mds_pim_memos-7.0.12.dist-info/top_level.txt
mds_pim_memos-7.0.12.dist-info/RECORD
